{"startdate":"20241105","fullstartdate":"202411052300","enddate":"20241106","url":"/th?id=OHR.ShiShiBeach_DE-DE0173093107_1920x1080.jpg&rf=LaDigue_1920x1080.jpg&pid=hp","urlbase":"/th?id=OHR.ShiShiBeach_DE-DE0173093107","copyright":"Shi Shi Beach im Olympic-Nationalpark, Washington, USA (© T.M. Schultze/TANDEM Stills + Motion)","copyrightlink":"https://www.bing.com/search?q=Olympic%2fNationalpark+Washington+&form=hpcapt&filters=HpDate%3a%2220241105_2300%22","title":"Magie des Abendlichts","quiz":"/search?q=Bing+homepage+quiz&filters=WQOskey:%22HPQuiz_20241105_ShiShiBeach%22&FORM=HPQUIZ","wp":true,"hsh":"a56ea8195a57fe4afddd09b0ae9fc21c","drk":1,"top":1,"bot":1,"hs":[]}