{"startdate":"20251023","fullstartdate":"202510232200","enddate":"20251024","url":"/th?id=OHR.StMangLibrary_DE-DE0881251342_1920x1080.jpg&rf=LaDigue_1920x1080.jpg&pid=hp","urlbase":"/th?id=OHR.StMangLibrary_DE-DE0881251342","copyright":"Alte Bibliothek, Kloster Sankt Mang, Füssen, Bayern (© marcobriviophoto/Shutterstock)","copyrightlink":"https://www.bing.com/search?q=Abtei+Sankt+Mang&form=hpcapt&filters=HpDate%3a%2220251023_2200%22","title":"Orte der Begegnung und Inspiration","quiz":"/search?q=Bing+homepage+quiz&filters=WQOskey:%22HPQuiz_20251023_StMangLibrary%22&FORM=HPQUIZ","wp":false,"hsh":"75d2198c2672ae36ebdbf38883345058","drk":1,"top":1,"bot":1,"hs":[]}