{"startdate":"20240226","fullstartdate":"202402261500","enddate":"20240227","url":"/th?id=OHR.PolarBearCubs_JA-JP0012953029_1920x1080.jpg&rf=LaDigue_1920x1080.jpg&pid=hp","urlbase":"/th?id=OHR.PolarBearCubs_JA-JP0012953029","copyright":"じゃれあうホッキョクグマの赤ちゃん, 米国 アラスカ州 (© Piriya Photography/Getty Images)","copyrightlink":"https://www.bing.com/search?q=%E3%81%98%E3%82%83%E3%82%8C%E3%81%82%E3%81%86%E3%83%9B%E3%83%83%E3%82%AD%E3%83%A7%E3%82%AF%E3%82%B0%E3%83%9E%E3%81%AE%E8%B5%A4%E3%81%A1%E3%82%83%E3%82%93&form=hpcapt&filters=HpDate%3a%2220240226_1500%22","title":"今日は国際ホッキョクグマの日","quiz":"/search?q=Bing+homepage+quiz&filters=WQOskey:%22HPQuiz_20240226_PolarBearCubs%22&FORM=HPQUIZ","wp":true,"hsh":"7324f4eb80248ae3ece64e1a47d8ac46","drk":1,"top":1,"bot":1,"hs":[]}