{"startdate":"20251120","fullstartdate":"202511201500","enddate":"20251121","url":"/th?id=OHR.SealWaving_JA-JP5482157523_1920x1080.jpg&rf=LaDigue_1920x1080.jpg&pid=hp","urlbase":"/th?id=OHR.SealWaving_JA-JP5482157523","copyright":"ゼニガタアザラシ, 米国 ニューヨーク州 (© Vicki Jauron, Babylon and Beyond Photography/Getty Images)","copyrightlink":"https://www.bing.com/search?q=%E4%B8%96%E7%95%8C%E3%83%8F%E3%83%AD%E3%83%BC%E3%83%BB%E3%83%87%E3%83%BC&form=hpcapt&filters=HpDate%3a%2220251120_1500%22","title":"今日は世界ハロー・デー","quiz":"/search?q=Bing+homepage+quiz&filters=WQOskey:%22HPQuiz_20251120_SealWaving%22&FORM=HPQUIZ","wp":true,"hsh":"c0ccbd186618e0e9e56139237633eee0","drk":1,"top":1,"bot":1,"hs":[]}