{"startdate":"20260430","fullstartdate":"202604301500","enddate":"20260501","url":"/th?id=OHR.GreenJasper_JA-JP1765702331_1920x1080.jpg&rf=LaDigue_1920x1080.jpg&pid=hp","urlbase":"/th?id=OHR.GreenJasper_JA-JP1765702331","copyright":"ジャスパー国立公園, カナダ (© Don White/Getty Images)","copyrightlink":"https://www.bing.com/search?q=%E3%82%B8%E3%83%A3%E3%82%B9%E3%83%91%E3%83%BC%E5%9B%BD%E7%AB%8B%E5%85%AC%E5%9C%92&form=hpcapt&filters=HpDate%3a%2220260430_1500%22","title":"自然が描く湖畔の景色","quiz":"/search?q=Bing+homepage+quiz&filters=WQOskey:%22HPQuiz_20260430_GreenJasper%22&FORM=HPQUIZ","wp":true,"hsh":"160ed49d16ee7b520292049559c4d16e","drk":1,"top":1,"bot":1,"hs":[]}