{"startdate":"20260123","fullstartdate":"202601231500","enddate":"20260124","url":"/th?id=OHR.AndermattSwiss_JA-JP9574225546_1920x1080.jpg&rf=LaDigue_1920x1080.jpg&pid=hp","urlbase":"/th?id=OHR.AndermattSwiss_JA-JP9574225546","copyright":"アンデルマット, スイス (© Xantana/Getty Images)","copyrightlink":"https://www.bing.com/search?q=%E3%82%A2%E3%83%B3%E3%83%87%E3%83%AB%E3%83%9E%E3%83%83%E3%83%88&form=hpcapt&filters=HpDate%3a%2220260123_1500%22","title":"雪に包まれた山村が輝く夜","quiz":"/search?q=Bing+homepage+quiz&filters=WQOskey:%22HPQuiz_20260123_AndermattSwiss%22&FORM=HPQUIZ","wp":true,"hsh":"eb85fda8017a3d6c31a4781aa7c40c94","drk":1,"top":1,"bot":1,"hs":[]}