{"startdate":"20260303","fullstartdate":"202603031500","enddate":"20260304","url":"/th?id=OHR.RilaCrocuses_JA-JP8929761168_1920x1080.jpg&rf=LaDigue_1920x1080.jpg&pid=hp","urlbase":"/th?id=OHR.RilaCrocuses_JA-JP8929761168","copyright":"紫クロッカス, ブルガリア (© Maya Karkalicheva/Getty Images)","copyrightlink":"https://www.bing.com/search?q=%E7%B4%AB%E3%82%AF%E3%83%AD%E3%83%83%E3%82%AB%E3%82%B9&form=hpcapt&filters=HpDate%3a%2220260303_1500%22","title":"残雪の山に咲く紫の小さな花","quiz":"/search?q=Bing+homepage+quiz&filters=WQOskey:%22HPQuiz_20260303_RilaCrocuses%22&FORM=HPQUIZ","wp":true,"hsh":"ebc55e886978d07228baf927bd40cfcd","drk":1,"top":1,"bot":1,"hs":[]}