{"startdate":"20250911","fullstartdate":"202509110700","enddate":"20250912","url":"/th?id=OHR.ExtremaduraJamon_ROW7444306308_1920x1080.jpg&rf=LaDigue_1920x1080.jpg&pid=hp","urlbase":"/th?id=OHR.ExtremaduraJamon_ROW7444306308","copyright":"Peña Falcon rock on the Tagus river, Monfragüe National Park, Spain (© Daniel Viñé Garcia/Getty Images)","copyrightlink":"https://www.bing.com/search?q=Monfrague+National+Park&form=hpcapt&filters=HpDate%3a%2220250911_0700%22","title":"Info","quiz":"/search?q=Bing+homepage+quiz&filters=WQOskey:%22HPQuiz_20250911_ExtremaduraJamon%22&FORM=HPQUIZ","wp":true,"hsh":"2ce62e4ece27c0c68d6bb8365a8e986b","drk":1,"top":1,"bot":1,"hs":[]}