{"startdate":"20230809","fullstartdate":"202308091830","enddate":"20230810","url":"/th?id=OHR.WorldLionDay_EN-IN7896417806_1920x1080.jpg&rf=LaDigue_1920x1080.jpg&pid=hp","urlbase":"/th?id=OHR.WorldLionDay_EN-IN7896417806","copyright":"A lion in Maasai Mara, Kenya (© Scott Davis/Tandem Stills + Motion)","copyrightlink":"https://www.bing.com/search?q=african+lion&form=hpcapt&filters=HpDate%3a%2220230809_1830%22","title":"'King of the jungle'? Nope","quiz":"/search?q=Bing+homepage+quiz&filters=WQOskey:%22HPQuiz_20230809_WorldLionDay%22&FORM=HPQUIZ","wp":true,"hsh":"fc3b2a4174f8e347b2178660d9c0a24a","drk":1,"top":1,"bot":1,"hs":[]}