{"startdate":"20231018","fullstartdate":"202310181830","enddate":"20231019","url":"/th?id=OHR.GoddessDurga_EN-IN0729980140_1920x1080.jpg&rf=LaDigue_1920x1080.jpg&pid=hp","urlbase":"/th?id=OHR.GoddessDurga_EN-IN0729980140","copyright":"Idols of Hindu gods and goddesses in Kumortuli, Kolkata, India.   (© Rob Pinney/Alamy Stock Photo)","copyrightlink":"https://www.bing.com/search?q=Durga+puja&form=hpcapt&filters=HpDate%3a%2220231018_1830%22","title":"A splendid saga","quiz":"/search?q=Bing+homepage+quiz&filters=WQOskey:%22HPQuiz_20231018_GoddessDurga%22&FORM=HPQUIZ","wp":true,"hsh":"f6d022d25a63ae491b58aca56bd39beb","drk":1,"top":1,"bot":1,"hs":[]}