{"startdate":"20240401","fullstartdate":"202404011830","enddate":"20240402","url":"/th?id=OHR.JutlandSpring_EN-IN7251097604_1920x1080.jpg&rf=LaDigue_1920x1080.jpg&pid=hp","urlbase":"/th?id=OHR.JutlandSpring_EN-IN7251097604","copyright":"Beech trees and wild anemones, Jutland, Denmark (© Nick Brundle Photography/Getty Images)","copyrightlink":"https://www.bing.com/search?q=Jutland+Denmark&form=hpcapt&filters=HpDate%3a%2220240401_1830%22","title":"Beneath a ray of light","quiz":"/search?q=Bing+homepage+quiz&filters=WQOskey:%22HPQuiz_20240401_JutlandSpring%22&FORM=HPQUIZ","wp":true,"hsh":"a1e6b409ea32af8ed2e53c460569d136","drk":1,"top":1,"bot":1,"hs":[]}