{"startdate":"20250724","fullstartdate":"202507242200","enddate":"20250725","url":"/th?id=OHR.LasPalmas_IT-IT1381176116_1920x1080.jpg&rf=LaDigue_1920x1080.jpg&pid=hp","urlbase":"/th?id=OHR.LasPalmas_IT-IT1381176116","copyright":"Vista aerea case colorate, Las Palmas de Gran Canaria, Spagna (© Marco Bottigelli/Getty Images)","copyrightlink":"https://www.bing.com/search?q=Las+Palmas+comune+spagnolo&form=hpcapt","title":"Colori e Armonia","quiz":"/search?q=Bing+homepage+quiz&filters=WQOskey:%22HPQuiz_20250724_LasPalmas%22&FORM=HPQUIZ","wp":true,"hsh":"669182f630bcf4aa87d54b0ce4d66a34","drk":1,"top":1,"bot":1,"hs":[]}