{"startdate":"20250513","fullstartdate":"202505132200","enddate":"20250514","url":"/th?id=OHR.SardiniaFlavia_IT-IT8830916850_1920x1080.jpg&rf=LaDigue_1920x1080.jpg&pid=hp","urlbase":"/th?id=OHR.SardiniaFlavia_IT-IT8830916850","copyright":"Porto Flavia, Iglesias, Sardegna (© Marco Bottigelli/Getty Images)","copyrightlink":"https://www.bing.com/search?q=Porto+Flavia&form=hpcapt","title":"Riflessioni Marine","quiz":"/search?q=Bing+homepage+quiz&filters=WQOskey:%22HPQuiz_20250513_SardiniaFlavia%22&FORM=HPQUIZ","wp":true,"hsh":"e733e194e8d68c19d5e8ffa0f277f75f","drk":1,"top":1,"bot":1,"hs":[]}