[{"startdate":"20230517","fullstartdate":"202305172200","enddate":"20230518","url":"/th?id=OHR.MuseoSoumaya_ES-ES7663567636_1920x1080.jpg&rf=LaDigue_1920x1080.jpg&pid=hp","urlbase":"/th?id=OHR.MuseoSoumaya_ES-ES7663567636","copyright":"Plaza Carso, Museo Soumaya, Ciudad de México, México (© Juan Romero/Alamy)","copyrightlink":"https://www.bing.com/search?q=Museo+Soumaya%2c+Ciudad+de+M%C3%A9xico%2c+M%C3%A9xico&form=hpcapt&filters=HpDate%3a%2220230517_2200%22","title":"La luz del sol convierte la plata en oro","quiz":"/search?q=Bing+homepage+quiz&filters=WQOskey:%22HPQuiz_20230517_MuseoSoumaya%22&FORM=HPQUIZ","wp":false,"hsh":"ab19810d98631da6575332d89747c183","drk":1,"top":1,"bot":1,"hs":[]},{"startdate":"20230518","fullstartdate":"202305182200","enddate":"20230519","url":"/th?id=OHR.SumatranRhino_ES-ES0481030773_1920x1080.jpg&rf=LaDigue_1920x1080.jpg&pid=hp","urlbase":"/th?id=OHR.SumatranRhino_ES-ES0481030773","copyright":"Rinoceronte de Sumatra, Parque Nacional de Way Kambas, Indonesia (© Cyril Ruoso/Minden Pictures)","copyrightlink":"https://www.bing.com/search?q=El+rinoceronte+de+Sumatra&form=hpcapt&filters=HpDate%3a%2220230518_2200%22","title":"¿Cómo podemos ayudar a estos animales?","quiz":"/search?q=Bing+homepage+quiz&filters=WQOskey:%22HPQuiz_20230518_SumatranRhino%22&FORM=HPQUIZ","wp":true,"hsh":"d419e8502a0f72959190c1dce090fec7","drk":1,"top":1,"bot":1,"hs":[]},{"startdate":"20230519","fullstartdate":"202305192200","enddate":"20230520","url":"/th?id=OHR.EuropeanHoneybee_ES-ES0636675084_1920x1080.jpg&rf=LaDigue_1920x1080.jpg&pid=hp","urlbase":"/th?id=OHR.EuropeanHoneybee_ES-ES0636675084","copyright":"Abejas europeas en Sheffield, Inglaterra, Reino Unido (© Deborah Vernon/Alamy)","copyrightlink":"https://www.bing.com/search?q=abejas+apis&form=hpcapt&filters=HpDate%3a%2220230519_2200%22","title":"Un zumbido muy especial","quiz":"/search?q=Bing+homepage+quiz&filters=WQOskey:%22HPQuiz_20230519_EuropeanHoneybee%22&FORM=HPQUIZ","wp":true,"hsh":"1ed8756252bad552000fa58ba2a13506","drk":1,"top":1,"bot":1,"hs":[]},{"startdate":"20230520","fullstartdate":"202305202200","enddate":"20230521","url":"/th?id=OHR.TempsFlors_ES-ES0333200681_1920x1080.jpg&rf=LaDigue_1920x1080.jpg&pid=hp","urlbase":"/th?id=OHR.TempsFlors_ES-ES0333200681","copyright":"Temps de Flors, Girona, Cataluña, España (© Scp photography/Shutterstock)","copyrightlink":"https://www.bing.com/search?q=Festival+en+Girona+Temps+de+Flor&form=hpcapt&filters=HpDate%3a%2220230520_2200%22","title":"Recorre las calles repletas de colores y aromas","quiz":"/search?q=Bing+homepage+quiz&filters=WQOskey:%22HPQuiz_20230520_TempsFlors%22&FORM=HPQUIZ","wp":true,"hsh":"d0dac4230c5c0374433b2f550313d4c8","drk":1,"top":1,"bot":1,"hs":[]},{"startdate":"20230521","fullstartdate":"202305212200","enddate":"20230522","url":"/th?id=OHR.BiodiverseCostaRica_ES-ES0838291190_1920x1080.jpg&rf=LaDigue_1920x1080.jpg&pid=hp","urlbase":"/th?id=OHR.BiodiverseCostaRica_ES-ES0838291190","copyright":"Volcán Arenal, La Fortuna de San Carlos, Costa Rica (© Kevin Wells/Getty Images)","copyrightlink":"https://www.bing.com/search?q=Volc%C3%A1n+Arenal%2c+La+Fortuna+de+San+Carlos%2c+Costa+Rica&form=hpcapt&filters=HpDate%3a%2220230521_2200%22","title":"¿Dónde está esta exuberante selva tropical?","quiz":"/search?q=Bing+homepage+quiz&filters=WQOskey:%22HPQuiz_20230521_BiodiverseCostaRica%22&FORM=HPQUIZ","wp":true,"hsh":"ebedc1ed6eda364a944519e54ed151d5","drk":1,"top":1,"bot":1,"hs":[]}]