{"startdate":"20250611","fullstartdate":"202506112200","enddate":"20250612","url":"/th?id=OHR.BigBendChisos_FR-FR3569892339_1920x1080.jpg&rf=LaDigue_1920x1080.jpg&pid=hp","urlbase":"/th?id=OHR.BigBendChisos_FR-FR3569892339","copyright":"Chisos Mountains, Parc national de Big Bend, Texas, État-Unis (© Dean Fikar/Getty Images)","copyrightlink":"https://www.bing.com/search?q=Parc+national+de+Big+Bend&form=hpcapt&filters=HpDate%3a%2220250611_2200%22","title":"Le désert aux trois visages","quiz":"/search?q=Bing+homepage+quiz&filters=WQOskey:%22HPQuiz_20250611_BigBendChisos%22&FORM=HPQUIZ","wp":true,"hsh":"ad3688d0669be0271ca064b6036c8b0c","drk":1,"top":1,"bot":1,"hs":[]}