{"startdate":"20251022","fullstartdate":"202510222200","enddate":"20251023","url":"/th?id=OHR.SnowLeopard_FR-FR6410501585_1920x1080.jpg&rf=LaDigue_1920x1080.jpg&pid=hp","urlbase":"/th?id=OHR.SnowLeopard_FR-FR6410501585","copyright":"Léopard des neiges avec ses petits, réserve de la biosphère du désert froid, Inde (© Oriol Alamany/naturepl.com)","copyrightlink":"https://www.bing.com/search?q=Journ%C3%A9e+internationale+du+l%C3%A9opard+des+neiges&form=hpcapt&filters=HpDate%3a%2220251022_2200%22","title":"Le maître du camouflage","quiz":"/search?q=Bing+homepage+quiz&filters=WQOskey:%22HPQuiz_20251022_SnowLeopard%22&FORM=HPQUIZ","wp":true,"hsh":"4e9df42ebfb942825acca0516ef57d09","drk":1,"top":1,"bot":1,"hs":[]}