{"startdate":"20260328","fullstartdate":"202603282300","enddate":"20260329","url":"/th?id=OHR.PeggysLighthouse_FR-FR2942871002_1920x1080.jpg&rf=LaDigue_1920x1080.jpg&pid=hp","urlbase":"/th?id=OHR.PeggysLighthouse_FR-FR2942871002","copyright":"Phare de Peggy’s Cove, Nouvelle-Écosse, Canada (© Prashanth Bala/Shutterstock)","copyrightlink":"https://www.bing.com/search?q=Phare+de+Peggy%E2%80%99s+Cove&form=hpcapt&filters=HpDate%3a%2220260328_2300%22","title":"Le calme en bord de mer","quiz":"/search?q=Bing+homepage+quiz&filters=WQOskey:%22HPQuiz_20260328_PeggysLighthouse%22&FORM=HPQUIZ","wp":true,"hsh":"088d317c26875aaafe74b465c30aacdc","drk":1,"top":1,"bot":1,"hs":[]}