{"startdate":"20260509","fullstartdate":"202605092200","enddate":"20260510","url":"/th?id=OHR.Fratercula_FR-FR5694797887_1920x1080.jpg&rf=LaDigue_1920x1080.jpg&pid=hp","urlbase":"/th?id=OHR.Fratercula_FR-FR5694797887","copyright":"Macareux moines, Pays de Galles (© FLPA/Alamy)","copyrightlink":"https://www.bing.com/search?q=macareux+moine&form=hpcapt&filters=HpDate%3a%2220260509_2200%22","title":"Plonger, s’envoler et survivre","quiz":"/search?q=Bing+homepage+quiz&filters=WQOskey:%22HPQuiz_20260509_Fratercula%22&FORM=HPQUIZ","wp":true,"hsh":"ef1790abc81bcacfc6f3a68d524e8caa","drk":1,"top":1,"bot":1,"hs":[]}