{"startdate":"20250613","fullstartdate":"202506132300","enddate":"20250614","url":"/th?id=OHR.TroopingTheColour2025_EN-GB7387782428_1920x1080.jpg&rf=LaDigue_1920x1080.jpg&pid=hp","urlbase":"/th?id=OHR.TroopingTheColour2025_EN-GB7387782428","copyright":"Trooping the Colour procession along The Mall in London, England, on June 16, 2007 (© Tim Graham Photo Library/Getty Images)","copyrightlink":"https://www.bing.com/search?q=Trooping+the+Colour&form=hpcapt&filters=HpDate%3a%2220250613_2300%22","title":"A royal birthday parade","quiz":"/search?q=Bing+homepage+quiz&filters=WQOskey:%22HPQuiz_20250613_TroopingTheColour2025%22&FORM=HPQUIZ","wp":false,"hsh":"1fe922ed95edc2b738d2b9fddefa9fc0","drk":1,"top":1,"bot":1,"hs":[]}