{"startdate":"20251208","fullstartdate":"202512080000","enddate":"20251209","url":"/th?id=OHR.ComoChristmas_EN-GB6672805340_1920x1080.jpg&rf=LaDigue_1920x1080.jpg&pid=hp","urlbase":"/th?id=OHR.ComoChristmas_EN-GB6672805340","copyright":"Christmas lights on buildings of Domaso, Lake Como, Italy (© Roberto Moiola/Getty Images)","copyrightlink":"https://www.bing.com/search?q=Lake+Como&form=hpcapt&filters=HpDate%3a%2220251208_0000%22","title":"All is calm, all is bright","quiz":"/search?q=Bing+homepage+quiz&filters=WQOskey:%22HPQuiz_20251208_ComoChristmas%22&FORM=HPQUIZ","wp":true,"hsh":"8f4962e874525b3b4a440d5ba3e0239b","drk":1,"top":1,"bot":1,"hs":[]}