{"startdate":"20241114","fullstartdate":"202411142300","enddate":"20241115","url":"/th?id=OHR.YiPengLanterns_ES-ES0717973586_1920x1080.jpg&rf=LaDigue_1920x1080.jpg&pid=hp","urlbase":"/th?id=OHR.YiPengLanterns_ES-ES0717973586","copyright":"Festival de los faroles de Yi Peng, Chiang Mai, Tailandia (© tampatra/Getty Images)","copyrightlink":"https://www.bing.com/search?q=Chiang+Mai+historia&form=hpcapt&filters=HpDate%3a%2220241114_2300%22","title":"La esperanza alza el vuelo","quiz":"/search?q=Bing+homepage+quiz&filters=WQOskey:%22HPQuiz_20241114_YiPengLanterns%22&FORM=HPQUIZ","wp":true,"hsh":"97d816654508a6f1048449e14d30734d","drk":1,"top":1,"bot":1,"hs":[]}