{"startdate":"20250420","fullstartdate":"202504202200","enddate":"20250421","url":"/th?id=OHR.JoshuaStars_ES-ES3139415437_1920x1080.jpg&rf=LaDigue_1920x1080.jpg&pid=hp","urlbase":"/th?id=OHR.JoshuaStars_ES-ES3139415437","copyright":"Árboles de Josué bajo la Vía Láctea, California, EE.UU. (© Chao Zhang/Getty Images)","copyrightlink":"https://www.bing.com/search?q=semana+internacional+del+cielo+oscuro&form=hpcapt&filters=HpDate%3a%2220250420_2200%22","title":"Bajo el encanto de la Vía Láctea","quiz":"/search?q=Bing+homepage+quiz&filters=WQOskey:%22HPQuiz_20250420_JoshuaStars%22&FORM=HPQUIZ","wp":true,"hsh":"5c4f71b4e61970025c4706fe87332a1c","drk":1,"top":1,"bot":1,"hs":[]}