{"startdate":"20250203","fullstartdate":"202502032300","enddate":"20250204","url":"/th?id=OHR.PrioratTarragona_ES-ES0211120786_1920x1080.jpg&rf=LaDigue_1920x1080.jpg&pid=hp","urlbase":"/th?id=OHR.PrioratTarragona_ES-ES0211120786","copyright":"Siurana de Tarragona, Cataluña, España (© Sergi Boixader/Alamy Stock Photo)","copyrightlink":"https://www.bing.com/search?q=Ciurana+de+Tarragona&form=hpcapt&filters=HpDate%3a%2220250203_2300%22","title":"¡Unas vistas que te dejarán helado!","quiz":"/search?q=Bing+homepage+quiz&filters=WQOskey:%22HPQuiz_20250203_PrioratTarragona%22&FORM=HPQUIZ","wp":true,"hsh":"fadcc8515e6d83ef590b11ba37d9995d","drk":1,"top":1,"bot":1,"hs":[]}