{"startdate":"20250305","fullstartdate":"202503052300","enddate":"20250306","url":"/th?id=OHR.NevadaBigHorns_ES-ES6947397352_1920x1080.jpg&rf=LaDigue_1920x1080.jpg&pid=hp","urlbase":"/th?id=OHR.NevadaBigHorns_ES-ES6947397352","copyright":"Borrego cimarrón del desierto en el Parque Estatal Valle del Fuego, Nevada, EE. UU. (© Rachid Dahnoun/Cavan Images)","copyrightlink":"https://www.bing.com/search?q=Parque+Estatal+Valle+del+Fuego&form=hpcapt&filters=HpDate%3a%2220250305_2300%22","title":"Una escalada compleja","quiz":"/search?q=Bing+homepage+quiz&filters=WQOskey:%22HPQuiz_20250305_NevadaBigHorns%22&FORM=HPQUIZ","wp":true,"hsh":"ebf3ca9f661aaf9227287d03b3d70410","drk":1,"top":1,"bot":1,"hs":[]}