{"startdate":"20260113","fullstartdate":"202601132300","enddate":"20260114","url":"/th?id=OHR.PalamidiFortress_ES-ES5609140401_1920x1080.jpg&rf=LaDigue_1920x1080.jpg&pid=hp","urlbase":"/th?id=OHR.PalamidiFortress_ES-ES5609140401","copyright":"Escalera de la Fortaleza de Palamidi, en Nauplia, Grecia (© George Pachantouris/Getty Images)","copyrightlink":"https://www.bing.com/search?q=Fortaleza+de+Palamidi&form=hpcapt&filters=HpDate%3a%2220260113_2300%22","title":"Ascendiendo por la historia","quiz":"/search?q=Bing+homepage+quiz&filters=WQOskey:%22HPQuiz_20260113_PalamidiFortress%22&FORM=HPQUIZ","wp":true,"hsh":"24b1fe45803a604ae255f3cc98e5b7f3","drk":1,"top":1,"bot":1,"hs":[]}