{"startdate":"20260217","fullstartdate":"202602172300","enddate":"20260218","url":"/th?id=OHR.PrzewalskisHorse_ES-ES3293960401_1920x1080.jpg&rf=LaDigue_1920x1080.jpg&pid=hp","urlbase":"/th?id=OHR.PrzewalskisHorse_ES-ES3293960401","copyright":"Caballos de Przewalski (© Nemyrivskyi Viacheslav/Getty Images)","copyrightlink":"https://www.bing.com/search?q=Caballo+de+Przewalski&form=hpcapt&filters=HpDate%3a%2220260217_2300%22","title":"Guardianes de la pradera","quiz":"/search?q=Bing+homepage+quiz&filters=WQOskey:%22HPQuiz_20260217_PrzewalskisHorse%22&FORM=HPQUIZ","wp":true,"hsh":"3f17b5ef5db5f6bad1dcda00d1e71568","drk":1,"top":1,"bot":1,"hs":[]}