{"startdate":"20240505","fullstartdate":"202405050400","enddate":"20240506","url":"/th?id=OHR.KalalochTree_EN-CA6384901158_1920x1080.jpg&rf=LaDigue_1920x1080.jpg&pid=hp","urlbase":"/th?id=OHR.KalalochTree_EN-CA6384901158","copyright":"Kalaloch Tree of Life, Kalaloch Beach, Olympic National Park, Washington (© Abbie Warnock-Matthews/Shutterstock)","copyrightlink":"https://www.bing.com/search?q=Olympic+National+Park&form=hpcapt&filters=HpDate%3a%2220240505_0400%22","title":"For tree's a jolly good fellow","quiz":"/search?q=Bing+homepage+quiz&filters=WQOskey:%22HPQuiz_20240505_KalalochTree%22&FORM=HPQUIZ","wp":true,"hsh":"0dfe9a79cfedf28f13b10ea294517c23","drk":1,"top":1,"bot":1,"hs":[]}