{"startdate":"20250504","fullstartdate":"202505040400","enddate":"20250505","url":"/th?id=OHR.SevilleNaboo_EN-CA6053548784_1920x1080.jpg&rf=LaDigue_1920x1080.jpg&pid=hp","urlbase":"/th?id=OHR.SevilleNaboo_EN-CA6053548784","copyright":"Plaza de España, Seville, Spain (© Horia Merla/Getty Images)","copyrightlink":"https://www.bing.com/search?q=Star+Wars+Day&form=hpcapt&filters=HpDate%3a%2220250504_0400%22","title":"Welcome to planet Naboo!","quiz":"/search?q=Bing+homepage+quiz&filters=WQOskey:%22HPQuiz_20250504_SevilleNaboo%22&FORM=HPQUIZ","wp":true,"hsh":"a915dc4f93207f90547ffbb63e6908ad","drk":1,"top":1,"bot":1,"hs":[]}