{"startdate":"20250915","fullstartdate":"202509150700","enddate":"20250916","url":"/th?id=OHR.Echasse_ROW7944797323_1920x1080.jpg&rf=LaDigue_1920x1080.jpg&pid=hp","urlbase":"/th?id=OHR.Echasse_ROW7944797323","copyright":"Black-winged stilts, France (© Antonio Sementa/500px/Getty Images)","copyrightlink":"https://www.bing.com/search?q=Black-winged+stilt&form=hpcapt","title":"Info","quiz":"/search?q=Bing+homepage+quiz&filters=WQOskey:%22HPQuiz_20250915_Echasse%22&FORM=HPQUIZ","wp":true,"hsh":"e602f90dd65d267504daf9547c28d679","drk":1,"top":1,"bot":1,"hs":[]}